lightning/__init__.py
lightning/classification.py
lightning/datasets.py
lightning/ranking.py
lightning/regression.py
lightning/setup.py
lightning/impl/__init__.py
lightning/impl/adagrad.py
lightning/impl/adagrad_fast.cp37-win_amd64.pyd
lightning/impl/base.py
lightning/impl/dataset_fast.cp37-win_amd64.pyd
lightning/impl/dataset_fast.pxd
lightning/impl/dual_cd.py
lightning/impl/dual_cd_fast.cp37-win_amd64.pyd
lightning/impl/fista.py
lightning/impl/loss_fast.cp37-win_amd64.pyd
lightning/impl/penalty.py
lightning/impl/prank.py
lightning/impl/prank_fast.cp37-win_amd64.pyd
lightning/impl/primal_cd.py
lightning/impl/primal_cd_fast.cp37-win_amd64.pyd
lightning/impl/primal_newton.py
lightning/impl/prox_fast.cp37-win_amd64.pyd
lightning/impl/prox_fast.pxd
lightning/impl/sag.py
lightning/impl/sag_fast.cp37-win_amd64.pyd
lightning/impl/sag_fast.pxd
lightning/impl/sdca.py
lightning/impl/sdca_fast.cp37-win_amd64.pyd
lightning/impl/setup.py
lightning/impl/sgd.py
lightning/impl/sgd_fast.cp37-win_amd64.pyd
lightning/impl/sgd_fast.pxd
lightning/impl/svrg.py
lightning/impl/svrg_fast.cp37-win_amd64.pyd
lightning/impl/datasets/__init__.py
lightning/impl/datasets/loaders.py
lightning/impl/datasets/samples_generator.py
lightning/impl/datasets/utils.py
lightning/impl/randomkit/__init__.py
lightning/impl/randomkit/random_fast.cp37-win_amd64.pyd
lightning/impl/randomkit/random_fast.pxd
lightning/impl/randomkit/randomkit.h
lightning/impl/randomkit/setup.py
lightning/impl/randomkit/tests/__init__.py
lightning/impl/randomkit/tests/test_random.py
lightning/impl/tests/__init__.py
lightning/impl/tests/conftest.py
lightning/impl/tests/test_adagrad.py
lightning/impl/tests/test_dataset.py
lightning/impl/tests/test_dual_cd.py
lightning/impl/tests/test_fista.py
lightning/impl/tests/test_penalty.py
lightning/impl/tests/test_prank.py
lightning/impl/tests/test_primal_cd.py
lightning/impl/tests/test_primal_newton.py
lightning/impl/tests/test_prox.py
lightning/impl/tests/test_sag.py
sklearn_contrib_lightning-0.6.2.post0.dist-info/METADATA
sklearn_contrib_lightning-0.6.2.post0.dist-info/WHEEL
sklearn_contrib_lightning-0.6.2.post0.dist-info/top_level.txt
sklearn_contrib_lightning-0.6.2.post0.dist-info/RECORD
