Metadata-Version: 2.1
Name: sklearn-contrib-lightning
Version: 0.6.2.post0
Summary: Large-scale sparse linear classification, regression and ranking in Python
Home-page: https://github.com/scikit-learn-contrib/lightning
Maintainer: Mathieu Blondel
Maintainer-email: mathieu@mblondel.org
License: new BSD
Download-URL: https://github.com/scikit-learn-contrib/lightning
Platform: UNKNOWN
Classifier: Intended Audience :: Science/Research
Classifier: Intended Audience :: Developers
Classifier: License :: OSI Approved
Classifier: Programming Language :: C
Classifier: Programming Language :: Python :: 3
Classifier: Topic :: Software Development
Classifier: Topic :: Scientific/Engineering
Classifier: Operating System :: Microsoft :: Windows
Classifier: Operating System :: POSIX
Classifier: Operating System :: Unix
Classifier: Operating System :: MacOS
Requires-Python: >=3.7
